chinesenumber/__init__.py
chinesenumber-0.1.1.dist-info/LICENSE
chinesenumber-0.1.1.dist-info/WHEEL
chinesenumber-0.1.1.dist-info/METADATA
chinesenumber-0.1.1.dist-info/RECORD
